vutils/__init__.py
vutils/gpt.py
vutils/log.py
vutils/mail.py
vutils/main.py
vutils/net.py
vutils/print_color.py
vutils/timer.py
vutils/data/__init__.py
vutils/data/language_recognizer.py
vutils/dl/__init__.py
vutils/dl/act.py
vutils/dl/base.py
vutils/dl/mlp.py
vutils/dl/ucm.py
vutils/dl/urm.py
vutils/dl/asr/__init__.py
vutils/dl/cv/__init__.py
vutils/dl/nlp/__init__.py
vutils/io/__init__.py
vutils/io/excel_handler.py
vutils/ml/__init__.py
vutils/ml/feature_selection/__init__.py
vutils/ml/feature_selection/relief.py
vutils/tools/__init__.py
vutils/tools/compare_two_file.py
vutils/tools/web_data_view.py
vutils-1.1.8.dist-info/METADATA
vutils-1.1.8.dist-info/WHEEL
vutils-1.1.8.dist-info/entry_points.txt
vutils-1.1.8.dist-info/top_level.txt
vutils-1.1.8.dist-info/RECORD
