Metadata-Version: 2.1
Name: vutils
Version: 1.1.8
Summary: vichayturen's utils
Home-page: https://github.com/RankKCodeTalker/vutils
Author: Vichayturen
Author-email: vichayturen@gmail.com
License: MIT
